collective.keycdn-1.0.0-py3.11-nspkg.pth
collective/keycdn/__init__.py
collective/keycdn/configure.zcml
collective/keycdn/interfaces.py
collective/keycdn/overrides.zcml
collective/keycdn/permissions.zcml
collective/keycdn/purger.py
collective/keycdn/setuphandlers.py
collective/keycdn/testing.py
collective/keycdn/browser/__init__.py
collective/keycdn/browser/configure.zcml
collective/keycdn/browser/controlpanel.py
collective/keycdn/browser/overrides/.gitkeep
collective/keycdn/browser/static/.gitkeep
collective/keycdn/locales/README.rst
collective/keycdn/locales/__init__.py
collective/keycdn/locales/collective.keycdn.pot
collective/keycdn/locales/update.py
collective/keycdn/locales/update.sh
collective/keycdn/locales/en/LC_MESSAGES/collective.keycdn.mo
collective/keycdn/locales/en/LC_MESSAGES/collective.keycdn.po
collective/keycdn/profiles/default/browserlayer.xml
collective/keycdn/profiles/default/catalog.xml
collective/keycdn/profiles/default/controlpanel.xml
collective/keycdn/profiles/default/metadata.xml
collective/keycdn/profiles/default/rolemap.xml
collective/keycdn/profiles/default/registry/main.xml
collective/keycdn/profiles/uninstall/browserlayer.xml
collective/keycdn/profiles/uninstall/controlpanel.xml
collective/keycdn/tests/__init__.py
collective/keycdn/tests/test_controlpanel.py
collective/keycdn/tests/test_purger.py
collective/keycdn/tests/test_setup.py
collective_keycdn-1.0.0.dist-info/licenses/LICENSE.GPL
collective_keycdn-1.0.0.dist-info/licenses/LICENSE.rst
collective_keycdn-1.0.0.dist-info/METADATA
collective_keycdn-1.0.0.dist-info/WHEEL
collective_keycdn-1.0.0.dist-info/entry_points.txt
collective_keycdn-1.0.0.dist-info/namespace_packages.txt
collective_keycdn-1.0.0.dist-info/top_level.txt
collective_keycdn-1.0.0.dist-info/RECORD
