Metadata-Version: 2.4
Name: collective.keycdn
Version: 1.0.0
Summary: A Plone addon for purging a KeyCDN cache on content changes.
Home-page: https://github.com/collective/collective.keycdn
Author: Jon Pentland
Author-email: jon.pentland@pretagov.co.uk
License: GPL version 2
Project-URL: PyPI, https://pypi.org/project/collective.keycdn/
Project-URL: Source, https://github.com/collective/collective.keycdn
Project-URL: Tracker, https://github.com/collective/collective.keycdn/issues
Keywords: Python Plone CMS KeyCDN
Classifier: Environment :: Web Environment
Classifier: Framework :: Plone
Classifier: Framework :: Plone :: Addon
Classifier: Framework :: Plone :: 5.2
Classifier: Framework :: Plone :: 6.0
Classifier: Programming Language :: Python
Classifier: Programming Language :: Python :: 3.7
Classifier: Programming Language :: Python :: 3.8
Classifier: Programming Language :: Python :: 3.9
Classifier: Operating System :: OS Independent
Classifier: License :: OSI Approved :: GNU General Public License v2 (GPLv2)
Requires-Python: >=3.7
License-File: LICENSE.GPL
License-File: LICENSE.rst
Requires-Dist: setuptools
Requires-Dist: z3c.jbot
Requires-Dist: z3c.unconfigure
Requires-Dist: plone.api>=1.8.4
Requires-Dist: plone.app.dexterity
Requires-Dist: plone.cachepurging
Requires-Dist: requests>=2.20.0
Provides-Extra: test
Requires-Dist: plone.app.testing; extra == "test"
Requires-Dist: plone.testing>=5.0.0; extra == "test"
Requires-Dist: plone.app.contenttypes; extra == "test"
Requires-Dist: plone.restapi; extra == "test"
Dynamic: author
Dynamic: author-email
Dynamic: classifier
Dynamic: description
Dynamic: home-page
Dynamic: keywords
Dynamic: license
Dynamic: license-file
Dynamic: project-url
Dynamic: provides-extra
Dynamic: requires-dist
Dynamic: requires-python
Dynamic: summary
